dps_jupyter_extension/__init__.py
dps_jupyter_extension/_version.py
dps_jupyter_extension-0.6.0.data/data/share/jupyter/labextensions/@maap-jupyterlab/dps-jupyter-extension/build_log.json
dps_jupyter_extension-0.6.0.data/data/share/jupyter/labextensions/@maap-jupyterlab/dps-jupyter-extension/package.json
dps_jupyter_extension-0.6.0.data/data/share/jupyter/labextensions/@maap-jupyterlab/dps-jupyter-extension/static/lib_index_js.4c1f19f7fb8c6f31bbf6.js
dps_jupyter_extension-0.6.0.data/data/share/jupyter/labextensions/@maap-jupyterlab/dps-jupyter-extension/static/lib_index_js.4c1f19f7fb8c6f31bbf6.js.map
dps_jupyter_extension-0.6.0.data/data/share/jupyter/labextensions/@maap-jupyterlab/dps-jupyter-extension/static/node_modules_babel_runtime_helpers_esm_extends_js-node_modules_babel_runtime_helpers_esm_obje-03121e.faa3e0cd2b6867c93671.js
dps_jupyter_extension-0.6.0.data/data/share/jupyter/labextensions/@maap-jupyterlab/dps-jupyter-extension/static/node_modules_babel_runtime_helpers_esm_extends_js-node_modules_babel_runtime_helpers_esm_obje-03121e.faa3e0cd2b6867c93671.js.map
dps_jupyter_extension-0.6.0.data/data/share/jupyter/labextensions/@maap-jupyterlab/dps-jupyter-extension/static/node_modules_babel_runtime_helpers_esm_objectSpread2_js.4818286c70ddf0e493f6.js
dps_jupyter_extension-0.6.0.data/data/share/jupyter/labextensions/@maap-jupyterlab/dps-jupyter-extension/static/node_modules_babel_runtime_helpers_esm_objectSpread2_js.4818286c70ddf0e493f6.js.map
dps_jupyter_extension-0.6.0.data/data/share/jupyter/labextensions/@maap-jupyterlab/dps-jupyter-extension/static/node_modules_react-is_index_js.ad9a3f9ad6b5bb3b008b.js
dps_jupyter_extension-0.6.0.data/data/share/jupyter/labextensions/@maap-jupyterlab/dps-jupyter-extension/static/node_modules_react-is_index_js.ad9a3f9ad6b5bb3b008b.js.map
dps_jupyter_extension-0.6.0.data/data/share/jupyter/labextensions/@maap-jupyterlab/dps-jupyter-extension/static/remoteEntry.cad4f49586358369bd70.js
dps_jupyter_extension-0.6.0.dist-info/METADATA
dps_jupyter_extension-0.6.0.dist-info/WHEEL
dps_jupyter_extension-0.6.0.dist-info/licenses/LICENSE
dps_jupyter_extension-0.6.0.dist-info/RECORD
